vnpy_optionmaster/__init__.py
vnpy_optionmaster/algo.py
vnpy_optionmaster/base.py
vnpy_optionmaster/engine.py
vnpy_optionmaster/time.py
vnpy_optionmaster/pricing/__init__.py
vnpy_optionmaster/pricing/binomial_tree.py
vnpy_optionmaster/pricing/binomial_tree_cython.cp313-win_amd64.pyd
vnpy_optionmaster/pricing/black_76.py
vnpy_optionmaster/pricing/black_76_cython.cp313-win_amd64.pyd
vnpy_optionmaster/pricing/black_scholes.py
vnpy_optionmaster/pricing/black_scholes_cython.cp313-win_amd64.pyd
vnpy_optionmaster/ui/__init__.py
vnpy_optionmaster/ui/chart.py
vnpy_optionmaster/ui/manager.py
vnpy_optionmaster/ui/monitor.py
vnpy_optionmaster/ui/option.ico
vnpy_optionmaster/ui/widget.py
vnpy_optionmaster-1.3.0.dist-info/METADATA
vnpy_optionmaster-1.3.0.dist-info/WHEEL
vnpy_optionmaster-1.3.0.dist-info/licenses/LICENSE
vnpy_optionmaster-1.3.0.dist-info/RECORD
