Metadata-Version: 2.4
Name: vnpy_optionmaster
Version: 1.3.0
Summary: Option pricing and trading application for VeighNa quant trading framework.
Project-URL: Homepage, https://www.vnpy.com
Project-URL: Documentation, https://www.vnpy.com/docs
Project-URL: Changes, https://github.com/vnpy/vnpy_optionmaster/blob/master/CHANGELOG.md
Project-URL: Source, https://github.com/vnpy/vnpy_optionmaster/
Project-URL: Forum, https://www.vnpy.com/forum
Author-email: Xiaoyou Chen <xiaoyou.chen@mail.vnpy.com>
License: MIT
License-File: LICENSE
Keywords: algotrading,investment,options,quant,quantitative,trading
Classifier: Development Status :: 5 - Production/Stable
Classifier: License :: OSI Approved :: MIT License
Classifier: Natural Language :: Chinese (Simplified)
Classifier: Operating System :: OS Independent
Classifier: Programming Language :: Python :: 3
Classifier: Programming Language :: Python :: 3.10
Classifier: Programming Language :: Python :: 3.11
Classifier: Programming Language :: Python :: 3.12
Classifier: Programming Language :: Python :: 3.13
Classifier: Programming Language :: Python :: Implementation :: CPython
Classifier: Topic :: Office/Business :: Financial :: Investment
Classifier: Typing :: Typed
Requires-Python: >=3.10
Requires-Dist: exchange-calendars>=4.10
Requires-Dist: matplotlib>=3.10.1
Requires-Dist: scipy>=1.15.2
Requires-Dist: vnpy>=4.0.0
